flask_openid_steam/ChangeLog
flask_openid_steam/docs/_static/flask-openid.png
flask_openid_steam/docs/conf.py
flask_openid_steam/docs/index.rst
flask_openid_steam/docs/make.bat
flask_openid_steam/docs/Makefile
flask_openid_steam/example/example.py
flask_openid_steam/example/README
flask_openid_steam/example/static/openid.png
flask_openid_steam/example/static/style.css
flask_openid_steam/example/templates/create_profile.html
flask_openid_steam/example/templates/edit_profile.html
flask_openid_steam/example/templates/index.html
flask_openid_steam/example/templates/layout.html
flask_openid_steam/example/templates/login.html
flask_openid_steam/flask_openid_steam.py
flask_openid_steam/LICENSE
flask_openid_steam/Makefile
flask_openid_steam/MANIFEST.in
flask_openid_steam/README.rst
flask_openid_steam/setup.cfg
flask_openid_steam/setup.py
flask_openid_steam-1.3.1.dist-info/METADATA
flask_openid_steam-1.3.1.dist-info/WHEEL
flask_openid_steam-1.3.1.dist-info/RECORD
