Metadata-Version: 2.1
Name: flask_openid_steam
Version: 1.3.1
Summary: Patched version of Flask-OpenID to support Steam OpenID without errors.
Author: Lukium
Author-email: mrlukium@outlook.com
Requires-Python: >=3.11,<4.0
Classifier: Programming Language :: Python :: 3
Classifier: Programming Language :: Python :: 3.11
Classifier: Programming Language :: Python :: 3.12
Requires-Dist: Flask (>=3.0.2,<4.0.0)
Requires-Dist: python3-openid (>=3.2.0,<4.0.0)
